tablesqlite/__init__.py
tablesqlite/py.typed
tablesqlite/query_wrappers.py
tablesqlite/utils.py
tablesqlite/action_queries/__init__.py
tablesqlite/action_queries/columns.py
tablesqlite/action_queries/tables.py
tablesqlite/info_queries/__init__.py
tablesqlite/info_queries/schema_parse.py
tablesqlite/info_queries/tables.py
tablesqlite/objects/__init__.py
tablesqlite/objects/generic.py
tablesqlite/objects/info_objects.py
tablesqlite/validation/__init__.py
tablesqlite/validation/custom_types.py
tablesqlite/validation/enforcers.py
tablesqlite/validation/names.py
tablesqlite/validation/path.py
tablesqlite/validation/sql_datatypes.py
tablesqlite-0.1.9.dist-info/licenses/LICENSE
tablesqlite-0.1.9.dist-info/METADATA
tablesqlite-0.1.9.dist-info/WHEEL
tablesqlite-0.1.9.dist-info/top_level.txt
tablesqlite-0.1.9.dist-info/RECORD
