Metadata-Version: 2.4
Name: tablesqlite
Version: 0.1.9
Summary: Declarative SQLite table builder and schema manager with integration support for recordsQL.
Author-email: Grayjou <cgrayjou@gmail.com>
License: MIT
Project-URL: Homepage, https://github.com/Grayjou/tablesqlite
Project-URL: Source, https://github.com/Grayjou/tablesqlite
Project-URL: Bug Tracker, https://github.com/Grayjou/tablesqlite/issues
Project-URL: Documentation, https://tablesqlite.readthedocs.io/
Project-URL: Changelog, https://github.com/Grayjou/tablesqlite/blob/main/CHANGELOG.md
Keywords: sqlite,sql,database,schema,table,ddl,orm,declarative
Classifier: Development Status :: 4 - Beta
Classifier: Intended Audience :: Developers
Classifier: License :: OSI Approved :: MIT License
Classifier: Operating System :: OS Independent
Classifier: Programming Language :: Python :: 3
Classifier: Programming Language :: Python :: 3.8
Classifier: Programming Language :: Python :: 3.9
Classifier: Programming Language :: Python :: 3.10
Classifier: Programming Language :: Python :: 3.11
Classifier: Programming Language :: Python :: 3.12
Classifier: Programming Language :: Python :: 3.13
Classifier: Programming Language :: Python :: 3.14
Classifier: Topic :: Database
Classifier: Topic :: Software Development :: Libraries :: Python Modules
Classifier: Typing :: Typed
Requires-Python: >=3.8
License-File: LICENSE
Requires-Dist: expressQL>=1.0.0
Requires-Dist: sortedcontainers>=2.4.0
Provides-Extra: dev
Requires-Dist: pytest>=7.0.0; extra == "dev"
Requires-Dist: mypy>=1.0.0; extra == "dev"
Requires-Dist: ruff>=0.1.0; extra == "dev"
Provides-Extra: docs
Requires-Dist: sphinx>=7.0.0; extra == "docs"
Requires-Dist: sphinx-rtd-theme>=2.0.0; extra == "docs"
Requires-Dist: sphinx-autodoc-typehints>=1.25.0; extra == "docs"
Dynamic: license-file
